{"match_id":"1bbf7cb8-b165-483c-b57b-aeeec3072ca4.nakama-0","map_id":"Lockdown","date":"February-11","humans":["86b019b9-dd32-4fe0-baf4-174a1f51fa68"],"bots":[],"duration_ms":609,"event_counts":{"Position":105,"Loot":18,"BotKill":1},"events":[{"uid":"86b019b9-dd32-4fe0-baf4-174a1f51fa68","bot":false,"x":-354.19,"z":-125.48,"px":149.3,"py":640.5,"t":0,"e":"Position"},{"uid":"86b019b9-dd32-4fe0-baf4-174a1f51fa68","bot":false,"x":-349.63,"z":-113.91,"px":154.0,"py":628.6,"t":35,"e":"Position"},{"uid":"86b019b9-dd32-4fe0-baf4-174a1f51fa68","bot":false,"x":-349.93,"z":-108.45,"px":153.7,"py":623.1,"t":40,"e":"Position"},{"uid":"86b019b9-dd32-4fe0-baf4-174a1f51fa68","bot":false,"x":-320.33,"z":-103.6,"px":184.0,"py":618.1,"t":45,"e":"Position"},{"uid":"86b019b9-dd32-4fe0-baf4-174a1f51fa68","bot":false,"x":-307.75,"z":-118.58,"px":196.9,"py":633.4,"t":50,"e":"Position"},{"uid":"86b019b9-dd32-4fe0-baf4-174a1f51fa68","bot":false,"x":-296.93,"z":-131.88,"px":207.9,"py":647.0,"t":55,"e":"Position"},{"uid":"86b019b9-dd32-4fe0-baf4-174a1f51fa68","bot":false,"x":-289.3,"z":-131.06,"px":215.8,"py":646.2,"t":60,"e":"Position"},{"uid":"86b019b9-dd32-4fe0-baf4-174a1f51fa68","bot":false,"x":-282.24,"z":-129.5,"px":223.0,"py":644.6,"t":71,"e":"Position"},{"uid":"86b019b9-dd32-4fe0-baf4-174a1f51fa68","bot":false,"x":-263.85,"z":-116.55,"px":241.8,"py":631.3,"t":76,"e":"Position"},{"uid":"86b019b9-dd32-4fe0-baf4-174a1f51fa68","bot":false,"x":-264.24,"z":-92.51,"px":241.4,"py":606.7,"t":81,"e":"Position"},{"uid":"86b019b9-dd32-4fe0-baf4-174a1f51fa68","bot":false,"x":-275.73,"z":-70.02,"px":229.6,"py":583.7,"t":86,"e":"Position"},{"uid":"86b019b9-dd32-4fe0-baf4-174a1f51fa68","bot":false,"x":-275.73,"z":-70.02,"px":229.6,"py":583.7,"t":87,"e":"Loot"},{"uid":"86b019b9-dd32-4fe0-baf4-174a1f51fa68","bot":false,"x":-292.27,"z":-90.85,"px":212.7,"py":605.0,"t":96,"e":"Position"},{"uid":"86b019b9-dd32-4fe0-baf4-174a1f51fa68","bot":false,"x":-305.53,"z":-110.32,"px":199.1,"py":625.0,"t":101,"e":"Position"},{"uid":"86b019b9-dd32-4fe0-baf4-174a1f51fa68","bot":false,"x":-303.56,"z":-112.55,"px":201.2,"py":627.2,"t":105,"e":"Loot"},{"uid":"86b019b9-dd32-4fe0-baf4-174a1f51fa68","bot":false,"x":-303.56,"z":-112.55,"px":201.2,"py":627.2,"t":106,"e":"Position"},{"uid":"86b019b9-dd32-4fe0-baf4-174a1f51fa68","bot":false,"x":-300.64,"z":-104.31,"px":204.1,"py":618.8,"t":111,"e":"Position"},{"uid":"86b019b9-dd32-4fe0-baf4-174a1f51fa68","bot":false,"x":-300.64,"z":-104.31,"px":204.1,"py":618.8,"t":112,"e":"Loot"},{"uid":"86b019b9-dd32-4fe0-baf4-174a1f51fa68","bot":false,"x":-294.18,"z":-109.92,"px":210.8,"py":624.6,"t":116,"e":"Position"},{"uid":"86b019b9-dd32-4fe0-baf4-174a1f51fa68","bot":false,"x":-293.3,"z":-110.01,"px":211.7,"py":624.6,"t":118,"e":"Loot"},{"uid":"86b019b9-dd32-4fe0-baf4-174a1f51fa68","bot":false,"x":-290.93,"z":-115.83,"px":214.1,"py":630.6,"t":121,"e":"Position"},{"uid":"86b019b9-dd32-4fe0-baf4-174a1f51fa68","bot":false,"x":-290.64,"z":-115.86,"px":214.4,"py":630.6,"t":121,"e":"Loot"},{"uid":"86b019b9-dd32-4fe0-baf4-174a1f51fa68","bot":false,"x":-292.53,"z":-116.55,"px":212.4,"py":631.3,"t":124,"e":"Loot"},{"uid":"86b019b9-dd32-4fe0-baf4-174a1f51fa68","bot":false,"x":-297.18,"z":-112.52,"px":207.7,"py":627.2,"t":128,"e":"Loot"},{"uid":"86b019b9-dd32-4fe0-baf4-174a1f51fa68","bot":false,"x":-299.59,"z":-102.82,"px":205.2,"py":617.3,"t":131,"e":"Position"},{"uid":"86b019b9-dd32-4fe0-baf4-174a1f51fa68","bot":false,"x":-287.54,"z":-104.41,"px":217.6,"py":618.9,"t":136,"e":"Position"},{"uid":"86b019b9-dd32-4fe0-baf4-174a1f51fa68","bot":false,"x":-302.83,"z":-92.32,"px":201.9,"py":606.5,"t":141,"e":"Position"},{"uid":"86b019b9-dd32-4fe0-baf4-174a1f51fa68","bot":false,"x":-316.37,"z":-97.83,"px":188.0,"py":612.2,"t":146,"e":"Position"},{"uid":"86b019b9-dd32-4fe0-baf4-174a1f51fa68","bot":false,"x":-316.53,"z":-89.47,"px":187.9,"py":603.6,"t":151,"e":"Position"},{"uid":"86b019b9-dd32-4fe0-baf4-174a1f51fa68","bot":false,"x":-297.39,"z":-63.4,"px":207.5,"py":576.9,"t":156,"e":"Position"},{"uid":"86b019b9-dd32-4fe0-baf4-174a1f51fa68","bot":false,"x":-271.57,"z":-69.63,"px":233.9,"py":583.3,"t":161,"e":"Position"},{"uid":"86b019b9-dd32-4fe0-baf4-174a1f51fa68","bot":false,"x":-264.27,"z":-79.92,"px":241.4,"py":593.8,"t":166,"e":"Position"},{"uid":"86b019b9-dd32-4fe0-baf4-174a1f51fa68","bot":false,"x":-235.82,"z":-71.11,"px":270.5,"py":584.8,"t":171,"e":"Position"},{"uid":"86b019b9-dd32-4fe0-baf4-174a1f51fa68","bot":false,"x":-214.82,"z":-74.02,"px":292.0,"py":587.8,"t":176,"e":"Position"},{"uid":"86b019b9-dd32-4fe0-baf4-174a1f51fa68","bot":false,"x":-204.23,"z":-78.38,"px":302.9,"py":592.3,"t":181,"e":"Position"},{"uid":"86b019b9-dd32-4fe0-baf4-174a1f51fa68","bot":false,"x":-197.2,"z":-76.31,"px":310.1,"py":590.1,"t":196,"e":"Position"},{"uid":"86b019b9-dd32-4fe0-baf4-174a1f51fa68","bot":false,"x":-190.25,"z":-55.98,"px":317.2,"py":569.3,"t":201,"e":"Position"},{"uid":"86b019b9-dd32-4fe0-baf4-174a1f51fa68","bot":false,"x":-185.63,"z":-67.92,"px":321.9,"py":581.5,"t":206,"e":"Position"},{"uid":"86b019b9-dd32-4fe0-baf4-174a1f51fa68","bot":false,"x":-182.19,"z":-71.01,"px":325.4,"py":584.7,"t":211,"e":"Position"},{"uid":"86b019b9-dd32-4fe0-baf4-174a1f51fa68","bot":false,"x":-177.1,"z":-62.64,"px":330.6,"py":576.1,"t":216,"e":"Position"},{"uid":"86b019b9-dd32-4fe0-baf4-174a1f51fa68","bot":false,"x":-169.27,"z":-64.24,"px":338.7,"py":577.8,"t":220,"e":"Loot"},{"uid":"86b019b9-dd32-4fe0-baf4-174a1f51fa68","bot":false,"x":-172.53,"z":-61.27,"px":335.3,"py":574.7,"t":221,"e":"Position"},{"uid":"86b019b9-dd32-4fe0-baf4-174a1f51fa68","bot":false,"x":-176.0,"z":-59.55,"px":331.8,"py":573.0,"t":223,"e":"Loot"},{"uid":"86b019b9-dd32-4fe0-baf4-174a1f51fa68","bot":false,"x":-178.79,"z":-55.51,"px":328.9,"py":568.8,"t":226,"e":"Position"},{"uid":"86b019b9-dd32-4fe0-baf4-174a1f51fa68","bot":false,"x":-174.0,"z":-70.84,"px":333.8,"py":584.5,"t":231,"e":"Position"},{"uid":"86b019b9-dd32-4fe0-baf4-174a1f51fa68","bot":false,"x":-163.74,"z":-90.76,"px":344.3,"py":604.9,"t":236,"e":"Position"},{"uid":"86b019b9-dd32-4fe0-baf4-174a1f51fa68","bot":false,"x":-159.31,"z":-104.41,"px":348.9,"py":618.9,"t":252,"e":"Position"},{"uid":"86b019b9-dd32-4fe0-baf4-174a1f51fa68","bot":false,"x":-139.31,"z":-109.89,"px":369.4,"py":624.5,"t":257,"e":"Position"},{"uid":"86b019b9-dd32-4fe0-baf4-174a1f51fa68","bot":false,"x":-125.07,"z":-125.79,"px":383.9,"py":640.8,"t":262,"e":"Position"},{"uid":"86b019b9-dd32-4fe0-baf4-174a1f51fa68","bot":false,"x":-125.13,"z":-114.83,"px":383.9,"py":629.6,"t":267,"e":"Position"},{"uid":"86b019b9-dd32-4fe0-baf4-174a1f51fa68","bot":false,"x":-146.28,"z":-113.9,"px":362.2,"py":628.6,"t":272,"e":"Position"},{"uid":"86b019b9-dd32-4fe0-baf4-174a1f51fa68","bot":false,"x":-143.88,"z":-106.76,"px":364.7,"py":621.3,"t":276,"e":"Loot"},{"uid":"86b019b9-dd32-4fe0-baf4-174a1f51fa68","bot":false,"x":-146.28,"z":-108.23,"px":362.2,"py":622.8,"t":277,"e":"Position"},{"uid":"86b019b9-dd32-4fe0-baf4-174a1f51fa68","bot":false,"x":-150.74,"z":-116.46,"px":357.6,"py":631.3,"t":282,"e":"Position"},{"uid":"86b019b9-dd32-4fe0-baf4-174a1f51fa68","bot":false,"x":-151.63,"z":-118.04,"px":356.7,"py":632.9,"t":283,"e":"Loot"},{"uid":"86b019b9-dd32-4fe0-baf4-174a1f51fa68","bot":false,"x":-153.31,"z":-113.07,"px":355.0,"py":627.8,"t":287,"e":"Position"},{"uid":"86b019b9-dd32-4fe0-baf4-174a1f51fa68","bot":false,"x":-159.45,"z":-101.28,"px":348.7,"py":615.7,"t":292,"e":"Position"},{"uid":"86b019b9-dd32-4fe0-baf4-174a1f51fa68","bot":false,"x":-161.84,"z":-105.21,"px":346.3,"py":619.7,"t":302,"e":"Position"},{"uid":"86b019b9-dd32-4fe0-baf4-174a1f51fa68","bot":false,"x":-164.18,"z":-104.55,"px":343.9,"py":619.1,"t":307,"e":"Position"},{"uid":"86b019b9-dd32-4fe0-baf4-174a1f51fa68","bot":false,"x":-177.61,"z":-98.01,"px":330.1,"py":612.4,"t":312,"e":"Position"},{"uid":"86b019b9-dd32-4fe0-baf4-174a1f51fa68","bot":false,"x":-175.38,"z":-106.38,"px":332.4,"py":620.9,"t":322,"e":"Position"},{"uid":"86b019b9-dd32-4fe0-baf4-174a1f51fa68","bot":false,"x":-178.5,"z":-97.34,"px":329.2,"py":611.7,"t":327,"e":"Position"},{"uid":"86b019b9-dd32-4fe0-baf4-174a1f51fa68","bot":false,"x":-196.71,"z":-100.62,"px":310.6,"py":615.0,"t":332,"e":"Position"},{"uid":"86b019b9-dd32-4fe0-baf4-174a1f51fa68","bot":false,"x":-202.69,"z":-84.88,"px":304.4,"py":598.9,"t":337,"e":"Position"},{"uid":"86b019b9-dd32-4fe0-baf4-174a1f51fa68","bot":false,"x":-205.93,"z":-81.86,"px":301.1,"py":595.8,"t":342,"e":"Position"},{"uid":"86b019b9-dd32-4fe0-baf4-174a1f51fa68","bot":false,"x":-202.93,"z":-81.8,"px":304.2,"py":595.8,"t":344,"e":"BotKill"},{"uid":"86b019b9-dd32-4fe0-baf4-174a1f51fa68","bot":false,"x":-202.78,"z":-81.66,"px":304.4,"py":595.6,"t":346,"e":"Loot"},{"uid":"86b019b9-dd32-4fe0-baf4-174a1f51fa68","bot":false,"x":-201.63,"z":-82.38,"px":305.5,"py":596.4,"t":347,"e":"Position"},{"uid":"86b019b9-dd32-4fe0-baf4-174a1f51fa68","bot":false,"x":-199.92,"z":-99.91,"px":307.3,"py":614.3,"t":352,"e":"Position"},{"uid":"86b019b9-dd32-4fe0-baf4-174a1f51fa68","bot":false,"x":-191.96,"z":-104.17,"px":315.4,"py":618.7,"t":357,"e":"Position"},{"uid":"86b019b9-dd32-4fe0-baf4-174a1f51fa68","bot":false,"x":-191.49,"z":-105.17,"px":315.9,"py":619.7,"t":361,"e":"Loot"},{"uid":"86b019b9-dd32-4fe0-baf4-174a1f51fa68","bot":false,"x":-193.0,"z":-106.33,"px":314.4,"py":620.9,"t":362,"e":"Position"},{"uid":"86b019b9-dd32-4fe0-baf4-174a1f51fa68","bot":false,"x":-192.76,"z":-101.32,"px":314.6,"py":615.8,"t":364,"e":"Loot"},{"uid":"86b019b9-dd32-4fe0-baf4-174a1f51fa68","bot":false,"x":-192.76,"z":-101.32,"px":314.6,"py":615.8,"t":365,"e":"Loot"},{"uid":"86b019b9-dd32-4fe0-baf4-174a1f51fa68","bot":false,"x":-192.62,"z":-103.41,"px":314.8,"py":617.9,"t":367,"e":"Position"},{"uid":"86b019b9-dd32-4fe0-baf4-174a1f51fa68","bot":false,"x":-190.13,"z":-113.36,"px":317.3,"py":628.1,"t":372,"e":"Position"},{"uid":"86b019b9-dd32-4fe0-baf4-174a1f51fa68","bot":false,"x":-177.18,"z":-127.64,"px":330.6,"py":642.7,"t":377,"e":"Position"},{"uid":"86b019b9-dd32-4fe0-baf4-174a1f51fa68","bot":false,"x":-187.06,"z":-124.84,"px":320.4,"py":639.8,"t":382,"e":"Position"},{"uid":"86b019b9-dd32-4fe0-baf4-174a1f51fa68","bot":false,"x":-167.76,"z":-141.44,"px":340.2,"py":656.8,"t":387,"e":"Position"},{"uid":"86b019b9-dd32-4fe0-baf4-174a1f51fa68","bot":false,"x":-138.38,"z":-145.58,"px":370.3,"py":661.1,"t":392,"e":"Position"},{"uid":"86b019b9-dd32-4fe0-baf4-174a1f51fa68","bot":false,"x":-120.36,"z":-155.84,"px":388.7,"py":671.6,"t":397,"e":"Position"},{"uid":"86b019b9-dd32-4fe0-baf4-174a1f51fa68","bot":false,"x":-91.45,"z":-163.82,"px":418.4,"py":679.7,"t":402,"e":"Position"},{"uid":"86b019b9-dd32-4fe0-baf4-174a1f51fa68","bot":false,"x":-66.41,"z":-144.18,"px":444.0,"py":659.6,"t":407,"e":"Position"},{"uid":"86b019b9-dd32-4fe0-baf4-174a1f51fa68","bot":false,"x":-55.6,"z":-141.7,"px":455.1,"py":657.1,"t":412,"e":"Position"},{"uid":"86b019b9-dd32-4fe0-baf4-174a1f51fa68","bot":false,"x":-53.74,"z":-143.8,"px":457.0,"py":659.3,"t":417,"e":"Position"},{"uid":"86b019b9-dd32-4fe0-baf4-174a1f51fa68","bot":false,"x":-48.67,"z":-143.62,"px":462.2,"py":659.1,"t":421,"e":"Loot"},{"uid":"86b019b9-dd32-4fe0-baf4-174a1f51fa68","bot":false,"x":-48.27,"z":-143.58,"px":462.6,"py":659.0,"t":423,"e":"Position"},{"uid":"86b019b9-dd32-4fe0-baf4-174a1f51fa68","bot":false,"x":-45.03,"z":-141.82,"px":465.9,"py":657.2,"t":426,"e":"Loot"},{"uid":"86b019b9-dd32-4fe0-baf4-174a1f51fa68","bot":false,"x":-44.47,"z":-141.42,"px":466.5,"py":656.8,"t":428,"e":"Position"},{"uid":"86b019b9-dd32-4fe0-baf4-174a1f51fa68","bot":false,"x":-41.04,"z":-121.98,"px":470.0,"py":636.9,"t":433,"e":"Position"},{"uid":"86b019b9-dd32-4fe0-baf4-174a1f51fa68","bot":false,"x":-44.89,"z":-115.66,"px":466.0,"py":630.4,"t":435,"e":"Loot"},{"uid":"86b019b9-dd32-4fe0-baf4-174a1f51fa68","bot":false,"x":-46.41,"z":-113.17,"px":464.5,"py":627.9,"t":438,"e":"Position"},{"uid":"86b019b9-dd32-4fe0-baf4-174a1f51fa68","bot":false,"x":-59.75,"z":-107.31,"px":450.8,"py":621.9,"t":443,"e":"Position"},{"uid":"86b019b9-dd32-4fe0-baf4-174a1f51fa68","bot":false,"x":-72.15,"z":-83.12,"px":438.1,"py":597.1,"t":448,"e":"Position"},{"uid":"86b019b9-dd32-4fe0-baf4-174a1f51fa68","bot":false,"x":-76.38,"z":-66.52,"px":433.8,"py":580.1,"t":453,"e":"Position"},{"uid":"86b019b9-dd32-4fe0-baf4-174a1f51fa68","bot":false,"x":-58.0,"z":-53.25,"px":452.6,"py":566.5,"t":458,"e":"Position"},{"uid":"86b019b9-dd32-4fe0-baf4-174a1f51fa68","bot":false,"x":-72.96,"z":-52.5,"px":437.3,"py":565.8,"t":463,"e":"Position"},{"uid":"86b019b9-dd32-4fe0-baf4-174a1f51fa68","bot":false,"x":-76.49,"z":-58.1,"px":433.7,"py":571.5,"t":468,"e":"Position"},{"uid":"86b019b9-dd32-4fe0-baf4-174a1f51fa68","bot":false,"x":-80.44,"z":-60.13,"px":429.6,"py":573.6,"t":478,"e":"Position"},{"uid":"86b019b9-dd32-4fe0-baf4-174a1f51fa68","bot":false,"x":-78.35,"z":-76.26,"px":431.8,"py":590.1,"t":483,"e":"Position"},{"uid":"86b019b9-dd32-4fe0-baf4-174a1f51fa68","bot":false,"x":-72.97,"z":-103.51,"px":437.3,"py":618.0,"t":488,"e":"Position"},{"uid":"86b019b9-dd32-4fe0-baf4-174a1f51fa68","bot":false,"x":-64.57,"z":-111.1,"px":445.9,"py":625.8,"t":493,"e":"Position"},{"uid":"86b019b9-dd32-4fe0-baf4-174a1f51fa68","bot":false,"x":-65.07,"z":-115.11,"px":445.4,"py":629.9,"t":498,"e":"Position"},{"uid":"86b019b9-dd32-4fe0-baf4-174a1f51fa68","bot":false,"x":-40.97,"z":-113.26,"px":470.0,"py":628.0,"t":508,"e":"Position"},{"uid":"86b019b9-dd32-4fe0-baf4-174a1f51fa68","bot":false,"x":-12.88,"z":-106.11,"px":498.8,"py":620.7,"t":513,"e":"Position"},{"uid":"86b019b9-dd32-4fe0-baf4-174a1f51fa68","bot":false,"x":6.73,"z":-80.93,"px":518.9,"py":594.9,"t":518,"e":"Position"},{"uid":"86b019b9-dd32-4fe0-baf4-174a1f51fa68","bot":false,"x":32.59,"z":-66.54,"px":545.4,"py":580.1,"t":523,"e":"Position"},{"uid":"86b019b9-dd32-4fe0-baf4-174a1f51fa68","bot":false,"x":41.62,"z":-60.83,"px":554.6,"py":574.3,"t":528,"e":"Position"},{"uid":"86b019b9-dd32-4fe0-baf4-174a1f51fa68","bot":false,"x":56.42,"z":-45.72,"px":569.8,"py":558.8,"t":533,"e":"Position"},{"uid":"86b019b9-dd32-4fe0-baf4-174a1f51fa68","bot":false,"x":77.84,"z":-27.97,"px":591.7,"py":540.6,"t":538,"e":"Position"},{"uid":"86b019b9-dd32-4fe0-baf4-174a1f51fa68","bot":false,"x":93.88,"z":-10.19,"px":608.1,"py":522.4,"t":543,"e":"Position"},{"uid":"86b019b9-dd32-4fe0-baf4-174a1f51fa68","bot":false,"x":124.39,"z":0.39,"px":639.4,"py":511.6,"t":548,"e":"Position"},{"uid":"86b019b9-dd32-4fe0-baf4-174a1f51fa68","bot":false,"x":152.38,"z":14.66,"px":668.0,"py":497.0,"t":553,"e":"Position"},{"uid":"86b019b9-dd32-4fe0-baf4-174a1f51fa68","bot":false,"x":154.49,"z":26.1,"px":670.2,"py":485.3,"t":558,"e":"Position"},{"uid":"86b019b9-dd32-4fe0-baf4-174a1f51fa68","bot":false,"x":168.58,"z":23.36,"px":684.6,"py":488.1,"t":563,"e":"Position"},{"uid":"86b019b9-dd32-4fe0-baf4-174a1f51fa68","bot":false,"x":171.49,"z":31.0,"px":687.6,"py":480.3,"t":568,"e":"Position"},{"uid":"86b019b9-dd32-4fe0-baf4-174a1f51fa68","bot":false,"x":169.79,"z":58.77,"px":685.9,"py":451.8,"t":573,"e":"Position"},{"uid":"86b019b9-dd32-4fe0-baf4-174a1f51fa68","bot":false,"x":179.15,"z":75.6,"px":695.5,"py":434.6,"t":578,"e":"Position"},{"uid":"86b019b9-dd32-4fe0-baf4-174a1f51fa68","bot":false,"x":198.86,"z":89.66,"px":715.6,"py":420.2,"t":583,"e":"Position"},{"uid":"86b019b9-dd32-4fe0-baf4-174a1f51fa68","bot":false,"x":223.63,"z":104.95,"px":741.0,"py":404.5,"t":588,"e":"Position"},{"uid":"86b019b9-dd32-4fe0-baf4-174a1f51fa68","bot":false,"x":250.57,"z":113.88,"px":768.6,"py":395.4,"t":593,"e":"Position"},{"uid":"86b019b9-dd32-4fe0-baf4-174a1f51fa68","bot":false,"x":273.91,"z":114.66,"px":792.5,"py":394.6,"t":599,"e":"Position"},{"uid":"86b019b9-dd32-4fe0-baf4-174a1f51fa68","bot":false,"x":298.12,"z":118.0,"px":817.3,"py":391.2,"t":604,"e":"Position"},{"uid":"86b019b9-dd32-4fe0-baf4-174a1f51fa68","bot":false,"x":317.34,"z":108.75,"px":837.0,"py":400.6,"t":609,"e":"Position"}]}